{
    "visit": {
        "active": 0,
        "gem_packs": [{
            "gems": 100,
            "cost": 10000
        },{
            "gems": 500,
            "cost": 50000
        },{
            "gems": 1000,
            "cost": 100000
        }]
    },

    "tiers": {
        "1": {
            "chance": 100,
            "rarity": "common",
            "gem_cost": 200,
            "items": [
                177, 207, 332, 335, 359, 366, 379, 
                422, 440, 482, 763, 769, 1304, 3009, 3087, 
                3144, 4000, 4010, 4542, 4543, 4544, 4545, 
                4546, 4547, 4548, 4549, 4550, 4551, 5043, 
                5088, 5190, 5209, 5212, 5214, 5554, 6006,
                6022, 9033, 9049
            ],
            "min_count": 4,
            "max_count": 4
        },
        "2": {
            "chance": 25,
            "gem_cost": 250,
            "rarity": "uncommon",
            "items": [
                126, 208, 275, 282, 332, 345, 387, 418, 491, 1015, 
                1383, 3161, 4018, 4339, 4345, 4374, 4648, 
                4803, 4838, 5040, 5128, 5414, 5581, 5590, 6111, 
                9062, 9126, 9314, 13017, 14444, 14714, 16009, 19151,
                21075, 380003, 380015, 380134, 380314, 380366
            ],
            "min_count": 3,
            "max_count": 5
        },
        "3": {
            "chance": 10,
            "gem_cost": 500,
            "rarity": "rare",
            "items": [
                112, 116, 171, 191, 219, 231, 235, 238, 427, 437, 453, 
                479, 488, 976, 999, 1856, 2130, 24069, 3023, 3257, 4141, 4686, 
                5027, 5208, 6120, 6135, 12099, 13010, 13142, 14051, 14074, 
                14563, 380033, 380034, 380043, 380096, 380097
            ],
            "min_count": 1,
            "max_count": 2 
        },
        "4": {
            "chance": 5,
            "gem_cost": 800,
            "rarity": "legendary",
            "items": [
                170, 173, 407, 215, 451, 4790, 11550, 15215, 370001, 380006,
                370002, 380082, 380138, 380139, 380142, 380291, 380296
            ],
            "min_count": 0,
            "max_count": 1 
        }
    }
}